fairsenseai/__init__.py
fairsenseai/analysis/__init__.py
fairsenseai/analysis/ai_governance.py
fairsenseai/analysis/ai_safety_dashboard.py
fairsenseai/analysis/bias.py
fairsenseai/analysis/risk_assessment.py
fairsenseai/analysis/save_embedding.py
fairsenseai/app.py
fairsenseai/dataframes_and_indexes/AI_RMF_playbook.csv
fairsenseai/dataframes_and_indexes/ai_rmf_index.faiss
fairsenseai/dataframes_and_indexes/preprocessed_risks_df.csv
fairsenseai/dataframes_and_indexes/risk_index.faiss
fairsenseai/runtime.py
fairsenseai/ui/about.html
fairsenseai/ui/footer.html
fairsenseai/ui/home.html
fairsenseai/utils/__init__.py
fairsenseai/utils/helper.py
fair_sense_ai-1.0.11.dist-info/LICENSE.md
fair_sense_ai-1.0.11.dist-info/METADATA
fair_sense_ai-1.0.11.dist-info/WHEEL
fair_sense_ai-1.0.11.dist-info/RECORD
