Metadata-Version: 2.3
Name: fair-sense-ai
Version: 1.0.11
Summary: 
License: Creative Commons BY-NC 4.0
Author: Shaina Raza, PhD
Author-email: shaina.raza@torontomu.ca
Requires-Python: >=3.10,<4.0
Classifier: License :: Other/Proprietary License
Classifier: Operating System :: OS Independent
Classifier: Programming Language :: Python :: 3
Classifier: Programming Language :: Python :: 3.10
Classifier: Programming Language :: Python :: 3.11
Classifier: Programming Language :: Python :: 3.12
Classifier: Programming Language :: Python :: 3.13
Requires-Dist: codecarbon (>=3.0.1,<4.0.0)
Requires-Dist: faiss-cpu (>=1.10.0,<2.0.0)
Requires-Dist: gradio (>=5,<6)
Requires-Dist: numpy (>=1.26,<2.0)
Requires-Dist: ollama (>=0.4.5,<0.5.0)
Requires-Dist: opencv-python (>=4.10.0.84,<5.0.0.0)
Requires-Dist: pandas (>=2.2.2,<3.0.0)
Requires-Dist: pillow (>=10.4,<11.0)
Requires-Dist: plotly (>=5.24.1,<6.0.0)
Requires-Dist: pytesseract (>=0.3.13,<0.4.0)
Requires-Dist: sentence-transformers (>=3.4.1,<4.0.0)
Requires-Dist: torch (>=2.2.2,<3.0.0)
Requires-Dist: torchvision (>=0.17.2,<0.18.0)
Requires-Dist: transformers (>=4.47.1,<4.51)
Project-URL: Documentation, https://vectorinstitute.github.io/FairSense-AI/
Project-URL: Repository, https://github.com/VectorInstitute/fair-sense-ai
